floriday_supplier_client/__init__.py
floriday_supplier_client/_version.py
floriday_supplier_client/api_client.py
floriday_supplier_client/api_factory.py
floriday_supplier_client/client.py
floriday_supplier_client/configuration.py
floriday_supplier_client/rest.py
floriday_supplier_client/api/__init__.py
floriday_supplier_client/api/additional_services_api.py
floriday_supplier_client/api/auction_api.py
floriday_supplier_client/api/base_items_api.py
floriday_supplier_client/api/batches_api.py
floriday_supplier_client/api/blanket_orders_api.py
floriday_supplier_client/api/bundled_offers_api.py
floriday_supplier_client/api/catalog_prices_api.py
floriday_supplier_client/api/collections_api.py
floriday_supplier_client/api/commercial_service_types_api.py
floriday_supplier_client/api/connections_api.py
floriday_supplier_client/api/contract_trade_item_groups_api.py
floriday_supplier_client/api/contracts_api.py
floriday_supplier_client/api/custom_packages_api.py
floriday_supplier_client/api/customer_offers_api.py
floriday_supplier_client/api/customer_stickers_api.py
floriday_supplier_client/api/delivery_condition_sets_api.py
floriday_supplier_client/api/delivery_locations_api.py
floriday_supplier_client/api/delivery_orders_api.py
floriday_supplier_client/api/direct_sales_api.py
floriday_supplier_client/api/domain_error_codes_api.py
floriday_supplier_client/api/flora_xchange_settings_api.py
floriday_supplier_client/api/fulfillment_orders_api.py
floriday_supplier_client/api/identities_api.py
floriday_supplier_client/api/invoice_lines_api.py
floriday_supplier_client/api/media_api.py
floriday_supplier_client/api/order_requests_api.py
floriday_supplier_client/api/organizations_api.py
floriday_supplier_client/api/packing_configuration_requests_api.py
floriday_supplier_client/api/plant_passports_api.py
floriday_supplier_client/api/price_groups_api.py
floriday_supplier_client/api/sales_order_correction_requests_api.py
floriday_supplier_client/api/sales_orders_api.py
floriday_supplier_client-0.2.3.dist-info/licenses/LICENSE
floriday_supplier_client-0.2.3.dist-info/METADATA
floriday_supplier_client-0.2.3.dist-info/WHEEL
floriday_supplier_client-0.2.3.dist-info/top_level.txt
floriday_supplier_client-0.2.3.dist-info/RECORD
