Metadata-Version: 2.4
Name: floriday-supplier-client
Version: 0.2.3
Summary: Main - Floriday Suppliers API
Home-page: 
Author-email: 
Keywords: Swagger,Main - Floriday Suppliers API
License-File: LICENSE
Requires-Dist: urllib3>=1.15
Requires-Dist: six>=1.10
Requires-Dist: certifi
Requires-Dist: python-dateutil
Dynamic: description
Dynamic: keywords
Dynamic: license-file
Dynamic: requires-dist
Dynamic: summary
